fits2tmp/__init__.py
fits2tmp/dask-output.log
fits2tmp/fits2tmp.py
fits2tmp/sdc2_100.fits
fits2tmp/sofiatestrewrite1002_cat.txt
fits2tmp/sofiatestrewrite1002_cat.xml
fits2tmp/sofiatestrewrite100_cat.txt
fits2tmp/sofiatestrewrite100_cat.xml
fits2tmp-0.2.0.dist-info/LICENSE
fits2tmp-0.2.0.dist-info/METADATA
fits2tmp-0.2.0.dist-info/WHEEL
fits2tmp-0.2.0.dist-info/RECORD
